hello_world_ccc/__init__.py
hello_world_ccc/client.py
hello_world_ccc-0.0.8.dist-info/LICENSE
hello_world_ccc-0.0.8.dist-info/METADATA
hello_world_ccc-0.0.8.dist-info/WHEEL
hello_world_ccc-0.0.8.dist-info/top_level.txt
hello_world_ccc-0.0.8.dist-info/RECORD
